main/__init__.py
main/api_handling/__init__.py
main/api_handling/google_handler.py
main/classes/LocationFactory.py
main/classes/__init__.py
main/classes/arc_solver.py
main/classes/decimal_location.py
main/classes/graph.py
main/classes/grid_location.py
main/classes/kml.py
main/classes/line_of_sight.py
main/classes/location.py
main/classes/non_decimal_location.py
main/view/__init__.py
main/view/gui.py
test/__init__.py
test/test_api_handling/__init__.py
test/test_api_handling/test_google_handler.py
test/test_classes/__init__.py
test/test_classes/test_arc_solver.py
test/test_classes/test_decimal_location.py
test/test_classes/test_graph.py
test/test_classes/test_grid_location.py
test/test_classes/test_location_factory.py
geographic_line_of_sight-1.0.3.dist-info/LICENSE
geographic_line_of_sight-1.0.3.dist-info/METADATA
geographic_line_of_sight-1.0.3.dist-info/WHEEL
geographic_line_of_sight-1.0.3.dist-info/top_level.txt
geographic_line_of_sight-1.0.3.dist-info/RECORD
