Metadata-Version: 2.1
Name: geographic-line-of-sight
Version: 1.0.3
Summary: A tool which uses google elevation API to batch process geographical line-of-sight calculations from .csv files
Home-page: https://github.com/MHenderson1988/line-of-sight-analysis
Author: Mark Henderson
Author-email: mark.henderson1988@gmail.com
License: UNKNOWN
Platform: UNKNOWN
Classifier: Programming Language :: Python :: 3
Classifier: License :: OSI Approved :: MIT License
Classifier: Operating System :: OS Independent
Requires-Python: >=3.6
